xls_updater/__about__.py
xls_updater/__init__.py
xls_updater/__main__.py
xls_updater/app.py
xls_updater/cli.py
xls_updater-0.2.6.dist-info/METADATA
xls_updater-0.2.6.dist-info/WHEEL
xls_updater-0.2.6.dist-info/entry_points.txt
xls_updater-0.2.6.dist-info/RECORD
