Metadata-Version: 2.3
Name: xls-updater
Version: 0.2.6
Summary: Convert legacy xls data to newer xlsx format.
Project-URL: homepage, https://github.com/Tranquility2/xls_updater
Project-URL: repository, https://github.com/Tranquility2/xls_updater
Author-email: Roy Moore <roy@moore.co.il>
Keywords: converter,excel,fileformat,spreadsheet,xls,xlsx
Classifier: Development Status :: 4 - Beta
Classifier: License :: OSI Approved :: MIT License
Classifier: Natural Language :: English
Classifier: Programming Language :: Python :: 3.10
Classifier: Programming Language :: Python :: 3.11
Classifier: Programming Language :: Python :: 3.12
Classifier: Topic :: File Formats
Classifier: Topic :: Office/Business :: Financial :: Spreadsheet
Requires-Python: >=3.10
Requires-Dist: click==8.1.7
Requires-Dist: openpyxl==3.1.2
Requires-Dist: tqdm==4.66.2
Requires-Dist: xlrd==2.0.1
Provides-Extra: bin
Requires-Dist: pyinstaller; extra == 'bin'
Provides-Extra: dev
Requires-Dist: black; extra == 'dev'
Requires-Dist: isort; extra == 'dev'
Requires-Dist: mypy; extra == 'dev'
Requires-Dist: pre-commit; extra == 'dev'
Requires-Dist: pylint; extra == 'dev'
Provides-Extra: release
Requires-Dist: build; extra == 'release'
Requires-Dist: semvergit; extra == 'release'
Requires-Dist: twine; extra == 'release'
Provides-Extra: test
Requires-Dist: humanize; extra == 'test'
Requires-Dist: pandas==2.*; extra == 'test'
Requires-Dist: pyarrow==15.*; extra == 'test'
Requires-Dist: pytest; extra == 'test'
Requires-Dist: pytest-cov; extra == 'test'
Requires-Dist: pytest-mock; extra == 'test'
Requires-Dist: xlwt==1.*; extra == 'test'
